gpgliblib/__init__.py
gpgliblib/base.py
gpgliblib/django.py
gpgliblib/gpgme.py
gpgliblib/pyme.py
gpgliblib/python_gnupg.py
gpgliblib/utils.py
gpgliblib-0.2.0.dist-info/DESCRIPTION.rst
gpgliblib-0.2.0.dist-info/METADATA
gpgliblib-0.2.0.dist-info/RECORD
gpgliblib-0.2.0.dist-info/WHEEL
gpgliblib-0.2.0.dist-info/metadata.json
gpgliblib-0.2.0.dist-info/top_level.txt
tests/__init__.py
tests/tests.py
